cheesepy_game/__init__.py
cheesepy_game/__main__.py
cheesepy_game/cell.py
cheesepy_game/cheese.py
cheesepy_game/config.py
cheesepy_game/exceptions.py
cheesepy_game/game_controller.py
cheesepy_game/game_levels.py
cheesepy_game/game_status.py
cheesepy_game/graphics.py
cheesepy_game/level.py
cheesepy_game/log.py
cheesepy_game/map_tools.py
cheesepy_game/maze_adaptor.py
cheesepy_game/messanger.py
cheesepy_game/password.py
cheesepy_game/position.py
cheesepy_game/shared_functions.py
cheesepy_game/victory.py
cheesepy_game/images/cheese.png
cheesepy_game/images/hole.png
cheesepy_game/images/mouse.png
cheesepy_game/images/strawberry.png
cheesepy_game/images/wall.png
cheesepy_game/maps/central_maze.ppm
cheesepy_game/maps/game_over.ppm
cheesepy_game/maps/level05.ppm
cheesepy_game/maps/level07.ppm
cheesepy_game/maps/maze.ppm
cheesepy_game/maps/stairs.ppm
cheesepy_game/maps/stairs_nested.ppm
cheesepy_game/maps/tunnel.ppm
cheesepy_game/maps/tunnel_monotone.ppm
cheesepy_game-1.1.30.dist-info/LICENCE.txt
cheesepy_game-1.1.30.dist-info/METADATA
cheesepy_game-1.1.30.dist-info/WHEEL
cheesepy_game-1.1.30.dist-info/top_level.txt
cheesepy_game-1.1.30.dist-info/RECORD
