Metadata-Version: 2.1
Name: cheesepy_game
Version: 1.1.30
Summary: A pedagogic Python game with mice and cheese
Author-email: Marco Pascucci <marpas.paris@gmail.com>
Project-URL: Homepage, https://mpascucci.github.io/CheesePy_Game/cheesepy_game.html
Project-URL: Source, https://github.com/mpascucci/CheesePy_Game
Classifier: Programming Language :: Python :: 3
Classifier: License :: OSI Approved :: GNU General Public License v3 (GPLv3)
Classifier: Operating System :: OS Independent
Requires-Python: >=3.10
License-File: LICENCE.txt
Requires-Dist: numpy >=1.22.4
Requires-Dist: pygame >=2.5.2
Requires-Dist: labyrinth-py >=1.0.4
